{
	"configurations" : 
	[
		{
			"directories" : 
			[
				{
					"build" : ".",
					"childIndexes" : 
					[
						1,
						2,
						3,
						4
					],
					"jsonFile" : "directory-.-Debug-d0094a50bb2071803777.json",
					"minimumCMakeVersion" : 
					{
						"string" : "3.27"
					},
					"projectIndex" : 0,
					"source" : ".",
					"targetIndexes" : 
					[
						4
					]
				},
				{
					"build" : "TCP",
					"jsonFile" : "directory-TCP-Debug-fc387c974655ff3a2d0a.json",
					"minimumCMakeVersion" : 
					{
						"string" : "3.27"
					},
					"parentIndex" : 0,
					"projectIndex" : 1,
					"source" : "TCP",
					"targetIndexes" : 
					[
						3
					]
				},
				{
					"build" : "Client",
					"jsonFile" : "directory-Client-Debug-32ce8e758cccb39b8cc7.json",
					"minimumCMakeVersion" : 
					{
						"string" : "3.27"
					},
					"parentIndex" : 0,
					"projectIndex" : 2,
					"source" : "Client",
					"targetIndexes" : 
					[
						0
					]
				},
				{
					"build" : "Server",
					"jsonFile" : "directory-Server-Debug-08cc111fca47106482c9.json",
					"minimumCMakeVersion" : 
					{
						"string" : "3.27"
					},
					"parentIndex" : 0,
					"projectIndex" : 3,
					"source" : "Server",
					"targetIndexes" : 
					[
						2
					]
				},
				{
					"build" : "SQLite",
					"jsonFile" : "directory-SQLite-Debug-b0c43d70db844150a619.json",
					"minimumCMakeVersion" : 
					{
						"string" : "3.27"
					},
					"parentIndex" : 0,
					"projectIndex" : 4,
					"source" : "SQLite",
					"targetIndexes" : 
					[
						1
					]
				}
			],
			"name" : "Debug",
			"projects" : 
			[
				{
					"childIndexes" : 
					[
						1,
						2,
						3,
						4
					],
					"directoryIndexes" : 
					[
						0
					],
					"name" : "all",
					"targetIndexes" : 
					[
						4
					]
				},
				{
					"directoryIndexes" : 
					[
						1
					],
					"name" : "TCP",
					"parentIndex" : 0,
					"targetIndexes" : 
					[
						3
					]
				},
				{
					"directoryIndexes" : 
					[
						2
					],
					"name" : "Client",
					"parentIndex" : 0,
					"targetIndexes" : 
					[
						0
					]
				},
				{
					"directoryIndexes" : 
					[
						3
					],
					"name" : "Server",
					"parentIndex" : 0,
					"targetIndexes" : 
					[
						2
					]
				},
				{
					"directoryIndexes" : 
					[
						4
					],
					"name" : "SQLite",
					"parentIndex" : 0,
					"targetIndexes" : 
					[
						1
					]
				}
			],
			"targets" : 
			[
				{
					"directoryIndex" : 2,
					"id" : "Client::@39d0ae6511a0d9878f7b",
					"jsonFile" : "target-Client-Debug-5bd2dabbc0c5d50fddf9.json",
					"name" : "Client",
					"projectIndex" : 2
				},
				{
					"directoryIndex" : 4,
					"id" : "SQLite::@d2b76298327718e4ac9b",
					"jsonFile" : "target-SQLite-Debug-857426522a073479db46.json",
					"name" : "SQLite",
					"projectIndex" : 4
				},
				{
					"directoryIndex" : 3,
					"id" : "Server::@20a40c4b36ca103854cb",
					"jsonFile" : "target-Server-Debug-d2fa17a1cfea6be22539.json",
					"name" : "Server",
					"projectIndex" : 3
				},
				{
					"directoryIndex" : 1,
					"id" : "TCP::@1e219276d713a2e72ab3",
					"jsonFile" : "target-TCP-Debug-a64d5245c055b445bf64.json",
					"name" : "TCP",
					"projectIndex" : 1
				},
				{
					"directoryIndex" : 0,
					"id" : "clean-all::@6890427a1f51a3e7e1df",
					"jsonFile" : "target-clean-all-Debug-ab75b241cfc7e98d30f0.json",
					"name" : "clean-all",
					"projectIndex" : 0
				}
			]
		}
	],
	"kind" : "codemodel",
	"paths" : 
	{
		"build" : "C:/CLionProjects/SC/cmake-build-debug",
		"source" : "C:/CLionProjects/SC"
	},
	"version" : 
	{
		"major" : 2,
		"minor" : 6
	}
}
